Workbook

Sheet Resumo
B2: Controle Financeiro · Resumo
B3: Clínica Sensi · Orçado x Realizado por grupo do orçamento
B5: Orçamento total (obra + ambientação) | C5: =SUMIFS('Orçado x Realizado'!$H$8:$H$98,'Orçado x Realizado'!$C$8:$C$98,1) -> 271962.96
B6: Realizado até o momento | C6: =SUM(Lançamentos!$O$7:$O$200) -> 7071.52
B7: Saldo do orçamento | C7: =C5-C6 -> 264891.44
B8: % executado | C8: =IF(C5=0,0,C6/C5) -> 0.026001776
B10: Grupo do orçamento | C10: Orçado (R$) | D10: Realizado (R$) | E10: Saldo (R$) | F10: % executado | G10: % do orçamento total
B11: 001.01 · Despesas indiretas | C11: =SUMIFS('Orçado x Realizado'!$H$8:$H$98,'Orçado x Realizado'!$B$8:$B$98,"001.01",'Orçado x Realizado'!$C$8:$C$98,2) -> 24985.62 | D11: =SUMIF(Lançamentos!$F$7:$F$200,"001.01*",Lançamentos!$O$7:$O$200) -> 0 | E11: =C11-D11 -> 24985.62 | F11: =IF(C11=0,0,D11/C11) -> 0 | G11: =IF($C$5=0,0,C11/$C$5) -> 0.091871409
B12: 001.02 · Serviços preliminares | C12: =SUMIFS('Orçado x Realizado'!$H$8:$H$98,'Orçado x Realizado'!$B$8:$B$98,"001.02",'Orçado x Realizado'!$C$8:$C$98,2) -> 8695.5596 | D12: =SUMIF(Lançamentos!$F$7:$F$200,"001.02*",Lançamentos!$O$7:$O$200) -> 0 | E12: =C12-D12 -> 8695.5596 | F12: =IF(C12=0,0,D12/C12) -> 0 | G12: =IF($C$5=0,0,C12/$C$5) -> 0.031973324
B13: 001.03 · Paredes e paineis | C13: =SUMIFS('Orçado x Realizado'!$H$8:$H$98,'Orçado x Realizado'!$B$8:$B$98,"001.03",'Orçado x Realizado'!$C$8:$C$98,2) -> 10849 | D13: =SUMIF(Lançamentos!$F$7:$F$200,"001.03*",Lançamentos!$O$7:$O$200) -> 0 | E13: =C13-D13 -> 10849 | F13: =IF(C13=0,0,D13/C13) -> 0 | G13: =IF($C$5=0,0,C13/$C$5) -> 0.039891462
B14: 001.04 · Forro de gesso | C14: =SUMIFS('Orçado x Realizado'!$H$8:$H$98,'Orçado x Realizado'!$B$8:$B$98,"001.04",'Orçado x Realizado'!$C$8:$C$98,2) -> 3420 | D14: =SUMIF(Lançamentos!$F$7:$F$200,"001.04*",Lançamentos!$O$7:$O$200) -> 0 | E14: =C14-D14 -> 3420 | F14: =IF(C14=0,0,D14/C14) -> 0 | G14: =IF($C$5=0,0,C14/$C$5) -> 0.012575242
B15: 001.05 · Esquadrias | C15: =SUMIFS('Orçado x Realizado'!$H$8:$H$98,'Orçado x Realizado'!$B$8:$B$98,"001.05",'Orçado x Realizado'!$C$8:$C$98,2) -> 6470 | D15: =SUMIF(Lançamentos!$F$7:$F$200,"001.05*",Lançamentos!$O$7:$O$200) -> 0 | E15: =C15-D15 -> 6470 | F15: =IF(C15=0,0,D15/C15) -> 0 | G15: =IF($C$5=0,0,C15/$C$5) -> 0.023790005
B16: 001.06 · Revestimentos | C16: =SUMIFS('Orçado x Realizado'!$H$8:$H$98,'Orçado x Realizado'!$B$8:$B$98,"001.06",'Orçado x Realizado'!$C$8:$C$98,2) -> 24342.736 | D16: =SUMIF(Lançamentos!$F$7:$F$200,"001.06*",Lançamentos!$O$7:$O$200) -> 2660.36 | E16: =C16-D16 -> 21682.376 | F16: =IF(C16=0,0,D16/C16) -> 0.10928763 | G16: =IF($C$5=0,0,C16/$C$5) -> 0.089507544
B17: 001.07 · Pintura | C17: =SUMIFS('Orçado x Realizado'!$H$8:$H$98,'Orçado x Realizado'!$B$8:$B$98,"001.07",'Orçado x Realizado'!$C$8:$C$98,2) -> 18185.804 | D17: =SUMIF(Lançamentos!$F$7:$F$200,"001.07*",Lançamentos!$O$7:$O$200) -> 0 | E17: =C17-D17 -> 18185.804 | F17: =IF(C17=0,0,D17/C17) -> 0 | G17: =IF($C$5=0,0,C17/$C$5) -> 0.066868679
B18: 001.08 · Pedras, louças e metais | C18: =SUMIFS('Orçado x Realizado'!$H$8:$H$98,'Orçado x Realizado'!$B$8:$B$98,"001.08",'Orçado x Realizado'!$C$8:$C$98,2) -> 12515.077 | D18: =SUMIF(Lançamentos!$F$7:$F$200,"001.08*",Lançamentos!$O$7:$O$200) -> 0 | E18: =C18-D18 -> 12515.077 | F18: =IF(C18=0,0,D18/C18) -> 0 | G18: =IF($C$5=0,0,C18/$C$5) -> 0.046017581
B19: 001.09 · Instalações | C19: =SUMIFS('Orçado x Realizado'!$H$8:$H$98,'Orçado x Realizado'!$B$8:$B$98,"001.09",'Orçado x Realizado'!$C$8:$C$98,2) -> 32986.26 | D19: =SUMIF(Lançamentos!$F$7:$F$200,"001.09*",Lançamentos!$O$7:$O$200) -> 4411.16 | E19: =C19-D19 -> 28575.1 | F19: =IF(C19=0,0,D19/C19) -> 0.13372719 | G19: =IF($C$5=0,0,C19/$C$5) -> 0.12128953
B20: 001.10 · Limpeza | C20: =SUMIFS('Orçado x Realizado'!$H$8:$H$98,'Orçado x Realizado'!$B$8:$B$98,"001.10",'Orçado x Realizado'!$C$8:$C$98,2) -> 1498.34 | D20: =SUMIF(Lançamentos!$F$7:$F$200,"001.10*",Lançamentos!$O$7:$O$200) -> 0 | E20: =C20-D20 -> 1498.34 | F20: =IF(C20=0,0,D20/C20) -> 0 | G20: =IF($C$5=0,0,C20/$C$5) -> 0.0055093533
B21: 002.01 · Ambientação | C21: =SUMIFS('Orçado x Realizado'!$H$8:$H$98,'Orçado x Realizado'!$B$8:$B$98,"002.01",'Orçado x Realizado'!$C$8:$C$98,2) -> 128014.56 | D21: =SUMIF(Lançamentos!$F$7:$F$200,"002.01*",Lançamentos!$O$7:$O$200) -> 0 | E21: =C21-D21 -> 128014.56 | F21: =IF(C21=0,0,D21/C21) -> 0 | G21: =IF($C$5=0,0,C21/$C$5) -> 0.47070587
B22: TOTAL | C22: =SUM(C11:C21) -> 271962.96 | D22: =SUM(D11:D21) -> 7071.52 | E22: =C22-D22 -> 264891.44 | F22: =IF(C22=0,0,D22/C22) -> 0.026001776 | G22: =SUM(G11:G21) -> 1
B24: Por centro de custo (nome livre informado nos lançamentos)
B25: Centro de custo | C25: Qtd. lançamentos | D25: Valor (R$)
B26: Instalações Frigorígenas | C26: =COUNTIF(Lançamentos!$E$7:$E$200,B26) -> 1 | D26: =SUMIF(Lançamentos!$E$7:$E$200,B26,Lançamentos!$O$7:$O$200) -> 4411.16
B27: Revestimento Cerâmico | C27: =COUNTIF(Lançamentos!$E$7:$E$200,B27) -> 1 | D27: =SUMIF(Lançamentos!$E$7:$E$200,B27,Lançamentos!$O$7:$O$200) -> 2660.36
B28: TOTAL | C28: =SUM(C26:C27) -> 2 | D28: =SUM(D26:D27) -> 7071.52
B30: Conferência: total realizado = soma dos lançamentos | D30: =IF(ROUND(D22-C6,2)=0,"OK","REVISAR: há lançamentos sem código EAP ou com código inválido") -> OK

Sheet Orçado x Realizado
B2: Orçado x Realizado · EAP Clínica Sensi
B3: Fonte do orçado: 'Clínica Sense - Orçamento Executivo.xlsm', aba EAP (proposta set/2026, BDI 0% e impostos 0%). Realizado: soma dos Lançamentos vinculados ao código (inclui subníveis).
B4: Níveis 1 a 3 somam automaticamente os itens de nível 4. Use os botões de agrupamento (+/−) à esquerda para recolher os itens.
B7: Código | C7: Nível | D7: Descrição | E7: Und | F7: Quant. | G7: Preço unit. (R$) | H7: Orçado (R$) | I7: Realizado (R$) | J7: Saldo (R$) | K7: % executado
B8: 001 | C8: 1 | D8: OBRA | H8: =SUMIFS($H$8:$H$98,$B$8:$B$98,B8&"*",$C$8:$C$98,4) -> 143948.4 | I8: =SUMIF(Lançamentos!$F$7:$F$200,B8&"*",Lançamentos!$O$7:$O$200) -> 7071.52 | J8: =H8-I8 -> 136876.88 | K8: =IF(H8=0,0,I8/H8) -> 0.049125382
B9: 001.01 | C9: 2 | D9: DESPESAS INDIRETAS | H9: =SUMIFS($H$8:$H$98,$B$8:$B$98,B9&"*",$C$8:$C$98,4) -> 24985.62 | I9: =SUMIF(Lançamentos!$F$7:$F$200,B9&"*",Lançamentos!$O$7:$O$200) -> 0 | J9: =H9-I9 -> 24985.62 | K9: =IF(H9=0,0,I9/H9) -> 0
B10: 001.01.01 | C10: 3 | D10: DESPESAS MENSAIS | H10: =SUMIFS($H$8:$H$98,$B$8:$B$98,B10&"*",$C$8:$C$98,4) -> 3185.62 | I10: =SUMIF(Lançamentos!$F$7:$F$200,B10&"*",Lançamentos!$O$7:$O$200) -> 0 | J10: =H10-I10 -> 3185.62 | K10: =IF(H10=0,0,I10/H10) -> 0
B11: 001.01.01.01 | C11: 4 | D11: ART | E11: VB | F11: 1 | G11: 200 | H11: 200 | I11: =SUMIF(Lançamentos!$F$7:$F$200,B11&"*",Lançamentos!$O$7:$O$200) -> 0 | J11: =H11-I11 -> 200 | K11: =IF(H11=0,0,I11/H11) -> 0
B12: 001.01.01.02 | C12: 4 | D12: CUSTOS COM CANTEIRO DE OBRAS | E12: OE | F12: 1 | G12: 985.62 | H12: 985.62 | I12: =SUMIF(Lançamentos!$F$7:$F$200,B12&"*",Lançamentos!$O$7:$O$200) -> 0 | J12: =H12-I12 -> 985.62 | K12: =IF(H12=0,0,I12/H12) -> 0
B13: 001.01.01.03 | C13: 4 | D13: MOBILIZAÇÃO, DESMOBILIZAÇÃO E FRETES DA OBRA | E13: VB | F13: 1 | G13: 2000 | H13: 2000 | I13: =SUMIF(Lançamentos!$F$7:$F$200,B13&"*",Lançamentos!$O$7:$O$200) -> 0 | J13: =H13-I13 -> 2000 | K13: =IF(H13=0,0,I13/H13) -> 0
B14: 001.01.02 | C14: 3 | D14: EQUIPE ADMININSTRATIVA | H14: =SUMIFS($H$8:$H$98,$B$8:$B$98,B14&"*",$C$8:$C$98,4) -> 17400 | I14: =SUMIF(Lançamentos!$F$7:$F$200,B14&"*",Lançamentos!$O$7:$O$200) -> 0 | J14: =H14-I14 -> 17400 | K14: =IF(H14=0,0,I14/H14) -> 0
B15: 001.01.02.01 | C15: 4 | D15: EQUIPE ADMINISTRATIVA | E15: OE | F15: 3 | G15: 5800 | H15: 17400 | I15: =SUMIF(Lançamentos!$F$7:$F$200,B15&"*",Lançamentos!$O$7:$O$200) -> 0 | J15: =H15-I15 -> 17400 | K15: =IF(H15=0,0,I15/H15) -> 0
B16: 001.01.03 | C16: 3 | D16: LOCAÇÃO DE EQUIPAMENTOS | H16: =SUMIFS($H$8:$H$98,$B$8:$B$98,B16&"*",$C$8:$C$98,4) -> 2400 | I16: =SUMIF(Lançamentos!$F$7:$F$200,B16&"*",Lançamentos!$O$7:$O$200) -> 0 | J16: =H16-I16 -> 2400 | K16: =IF(H16=0,0,I16/H16) -> 0
B17: 001.01.03.01 | C17: 4 | D17: LOCAÇÃO DE EQUIPAMENTOS E MÁQUINA | E17: OE | F17: 1 | G17: 2400 | H17: 2400 | I17: =SUMIF(Lançamentos!$F$7:$F$200,B17&"*",Lançamentos!$O$7:$O$200) -> 0 | J17: =H17-I17 -> 2400 | K17: =IF(H17=0,0,I17/H17) -> 0
B18: 001.01.04 | C18: 3 | D18: ELABORAÇÃO DE PROJETOS | H18: =SUMIFS($H$8:$H$98,$B$8:$B$98,B18&"*",$C$8:$C$98,4) -> 2000 | I18: =SUMIF(Lançamentos!$F$7:$F$200,B18&"*",Lançamentos!$O$7:$O$200) -> 0 | J18: =H18-I18 -> 2000 | K18: =IF(H18=0,0,I18/H18) -> 0
B19: 001.01.04.01 | C19: 4 | D19: CUSTOS COM ELABORAÇÃO DE PROJETOS COMPLEMENTARES | E19: VB | F19: 1 | G19: 2000 | H19: 2000 | I19: =SUMIF(Lançamentos!$F$7:$F$200,B19&"*",Lançamentos!$O$7:$O$200) -> 0 | J19: =H19-I19 -> 2000 | K19: =IF(H19=0,0,I19/H19) -> 0
B20: 001.02 | C20: 2 | D20: SERVIÇOS PRELIMINARES | H20: =SUMIFS($H$8:$H$98,$B$8:$B$98,B20&"*",$C$8:$C$98,4) -> 8695.5596 | I20: =SUMIF(Lançamentos!$F$7:$F$200,B20&"*",Lançamentos!$O$7:$O$200) -> 0 | J20: =H20-I20 -> 8695.5596 | K20: =IF(H20=0,0,I20/H20) -> 0
B21: 001.02.01 | C21: 3 | D21: SERVIÇOS PRELIMINARES | H21: =SUMIFS($H$8:$H$98,$B$8:$B$98,B21&"*",$C$8:$C$98,4) -> 8695.5596 | I21: =SUMIF(Lançamentos!$F$7:$F$200,B21&"*",Lançamentos!$O$7:$O$200) -> 0 | J21: =H21-I21 -> 8695.5596 | K21: =IF(H21=0,0,I21/H21) -> 0
B22: 001.02.01.01 | C22: 4 | D22: DEMOLIÇÃO E TRANSPORTE DE PISO CERÂMICO SOBRE CONTRAPISO | E22: M2 | F22: 39.4259 | G22: 71.44632 | H22: 2816.8355 | I22: =SUMIF(Lançamentos!$F$7:$F$200,B22&"*",Lançamentos!$O$7:$O$200) -> 0 | J22: =H22-I22 -> 2816.8355 | K22: =IF(H22=0,0,I22/H22) -> 0
B23: 001.02.01.02 | C23: 4 | D23: EXECUÇÃO DE LIXAMENTO E LIMPEZA DE CONTRAPISO AUTONIVELANTE | E23: M2 | F23: 39.4259 | G23: 1.9848528 | H23: 78.254608 | I23: =SUMIF(Lançamentos!$F$7:$F$200,B23&"*",Lançamentos!$O$7:$O$200) -> 0 | J23: =H23-I23 -> 78.254608 | K23: =IF(H23=0,0,I23/H23) -> 0
B24: 001.02.01.03 | C24: 4 | D24: DEMOLIÇÃO E TRANSPORTE DE FORRO DE GESSO ALT. ATÉ 3,00M | E24: M2 | F24: 39.4259 | G24: 49.16736 | H24: 1938.4674 | I24: =SUMIF(Lançamentos!$F$7:$F$200,B24&"*",Lançamentos!$O$7:$O$200) -> 0 | J24: =H24-I24 -> 1938.4674 | K24: =IF(H24=0,0,I24/H24) -> 0
B25: 001.02.01.04 | C25: 4 | D25: REMOÇÃO DE BANCADAS | E25: M2 | F25: 5 | G25: 44.55792 | H25: 222.7896 | I25: =SUMIF(Lançamentos!$F$7:$F$200,B25&"*",Lançamentos!$O$7:$O$200) -> 0 | J25: =H25-I25 -> 222.7896 | K25: =IF(H25=0,0,I25/H25) -> 0
B26: 001.02.01.05 | C26: 4 | D26: REMOÇÃO DE RESÍDUOS | E26: M3 | F26: 18 | G26: 122.5 | H26: 2205 | I26: =SUMIF(Lançamentos!$F$7:$F$200,B26&"*",Lançamentos!$O$7:$O$200) -> 0 | J26: =H26-I26 -> 2205 | K26: =IF(H26=0,0,I26/H26) -> 0
B27: 001.02.01.06 | C27: 4 | D27: PROTEÇÃO DE PISO COM SALVA PISO | E27: M2 | F27: 93.0659 | G27: 15.41072 | H27: 1434.2125 | I27: =SUMIF(Lançamentos!$F$7:$F$200,B27&"*",Lançamentos!$O$7:$O$200) -> 0 | J27: =H27-I27 -> 1434.2125 | K27: =IF(H27=0,0,I27/H27) -> 0
B28: 001.03 | C28: 2 | D28: PAREDES E PAINEIS | H28: =SUMIFS($H$8:$H$98,$B$8:$B$98,B28&"*",$C$8:$C$98,4) -> 10849 | I28: =SUMIF(Lançamentos!$F$7:$F$200,B28&"*",Lançamentos!$O$7:$O$200) -> 0 | J28: =H28-I28 -> 10849 | K28: =IF(H28=0,0,I28/H28) -> 0
B29: 001.03.01 | C29: 3 | D29: DIVISÓRIA DE GESSO | H29: =SUMIFS($H$8:$H$98,$B$8:$B$98,B29&"*",$C$8:$C$98,4) -> 10849 | I29: =SUMIF(Lançamentos!$F$7:$F$200,B29&"*",Lançamentos!$O$7:$O$200) -> 0 | J29: =H29-I29 -> 10849 | K29: =IF(H29=0,0,I29/H29) -> 0
B30: 001.03.01.01 | C30: 4 | D30: FORNECIMENTO E EXECUÇÃO DE DRYWALL E LÃ DE VIDRO - TERCEIRIZADO | E30: M2 | F30: 39.6462 | G30: 160.14145 | H30: 6349 | I30: =SUMIF(Lançamentos!$F$7:$F$200,B30&"*",Lançamentos!$O$7:$O$200) -> 0 | J30: =H30-I30 -> 6349 | K30: =IF(H30=0,0,I30/H30) -> 0
B31: 001.03.01.02 | C31: 4 | D31: FORNECIMENTO E EXECUÇÃO DE ELEMENTOS DECORATIVOS EM GESSO | E31: VB | F31: 1 | G31: 4500 | H31: 4500 | I31: =SUMIF(Lançamentos!$F$7:$F$200,B31&"*",Lançamentos!$O$7:$O$200) -> 0 | J31: =H31-I31 -> 4500 | K31: =IF(H31=0,0,I31/H31) -> 0
B32: 001.04 | C32: 2 | D32: FORRO DE GESSO | H32: =SUMIFS($H$8:$H$98,$B$8:$B$98,B32&"*",$C$8:$C$98,4) -> 3420 | I32: =SUMIF(Lançamentos!$F$7:$F$200,B32&"*",Lançamentos!$O$7:$O$200) -> 0 | J32: =H32-I32 -> 3420 | K32: =IF(H32=0,0,I32/H32) -> 0
B33: 001.04.01 | C33: 3 | D33: FORRO DE GESSO | H33: =SUMIFS($H$8:$H$98,$B$8:$B$98,B33&"*",$C$8:$C$98,4) -> 3420 | I33: =SUMIF(Lançamentos!$F$7:$F$200,B33&"*",Lançamentos!$O$7:$O$200) -> 0 | J33: =H33-I33 -> 3420 | K33: =IF(H33=0,0,I33/H33) -> 0
B34: 001.04.01.01 | C34: 4 | D34: FORNECIMENTO E EXECUÇÃO DE FORRO DE GESSO ACARTONADO FGE | E34: M2 | F34: 37.6582 | G34: 90.816874 | H34: 3420 | I34: =SUMIF(Lançamentos!$F$7:$F$200,B34&"*",Lançamentos!$O$7:$O$200) -> 0 | J34: =H34-I34 -> 3420 | K34: =IF(H34=0,0,I34/H34) -> 0
B35: 001.05 | C35: 2 | D35: ESQUADRIAS | H35: =SUMIFS($H$8:$H$98,$B$8:$B$98,B35&"*",$C$8:$C$98,4) -> 6470 | I35: =SUMIF(Lançamentos!$F$7:$F$200,B35&"*",Lançamentos!$O$7:$O$200) -> 0 | J35: =H35-I35 -> 6470 | K35: =IF(H35=0,0,I35/H35) -> 0
B36: 001.05.01 | C36: 3 | D36: ESQUADRIAS DE ALUMÍNIO E VIDRO | H36: =SUMIFS($H$8:$H$98,$B$8:$B$98,B36&"*",$C$8:$C$98,4) -> 720 | I36: =SUMIF(Lançamentos!$F$7:$F$200,B36&"*",Lançamentos!$O$7:$O$200) -> 0 | J36: =H36-I36 -> 720 | K36: =IF(H36=0,0,I36/H36) -> 0
B37: 001.05.01.01 | C37: 4 | D37: FORNECIMENTO E MONTAGEM DE ESQUADRIA FIXA | E37: M2 | F37: 0.9 | G37: 800 | H37: 720 | I37: =SUMIF(Lançamentos!$F$7:$F$200,B37&"*",Lançamentos!$O$7:$O$200) -> 0 | J37: =H37-I37 -> 720 | K37: =IF(H37=0,0,I37/H37) -> 0
B38: 001.05.02 | C38: 3 | D38: ESQUADRIAS DE MADEIRA | H38: =SUMIFS($H$8:$H$98,$B$8:$B$98,B38&"*",$C$8:$C$98,4) -> 5750 | I38: =SUMIF(Lançamentos!$F$7:$F$200,B38&"*",Lançamentos!$O$7:$O$200) -> 0 | J38: =H38-I38 -> 5750 | K38: =IF(H38=0,0,I38/H38) -> 0
B39: 001.05.02.01 | C39: 4 | D39: FORNECIMENTO E MONTAGEM DE PORTA DE MADEIRA 70X210 (PARANÁ) - INCLUSO FERRAGENS (ABRIR) | E39: UND | F39: 3 | G39: 1150 | H39: 3450 | I39: =SUMIF(Lançamentos!$F$7:$F$200,B39&"*",Lançamentos!$O$7:$O$200) -> 0 | J39: =H39-I39 -> 3450 | K39: =IF(H39=0,0,I39/H39) -> 0
B40: 001.05.02.02 | C40: 4 | D40: FORNECIMENTO E MONTAGEM DE PORTA DE MADEIRA 60X210 (PARANÁ) - INCLUSO FERRAGENS (CORRER) | E40: UND | F40: 2 | G40: 1150 | H40: 2300 | I40: =SUMIF(Lançamentos!$F$7:$F$200,B40&"*",Lançamentos!$O$7:$O$200) -> 0 | J40: =H40-I40 -> 2300 | K40: =IF(H40=0,0,I40/H40) -> 0
B41: 001.06 | C41: 2 | D41: REVESTIMENTOS | H41: =SUMIFS($H$8:$H$98,$B$8:$B$98,B41&"*",$C$8:$C$98,4) -> 24342.736 | I41: =SUMIF(Lançamentos!$F$7:$F$200,B41&"*",Lançamentos!$O$7:$O$200) -> 2660.36 | J41: =H41-I41 -> 21682.376 | K41: =IF(H41=0,0,I41/H41) -> 0.10928763
B42: 001.06.01 | C42: 3 | D42: REVESTIMENTO DE PISO | H42: =SUMIFS($H$8:$H$98,$B$8:$B$98,B42&"*",$C$8:$C$98,4) -> 14550.92 | I42: =SUMIF(Lançamentos!$F$7:$F$200,B42&"*",Lançamentos!$O$7:$O$200) -> 2660.36 | J42: =H42-I42 -> 11890.56 | K42: =IF(H42=0,0,I42/H42) -> 0.18283105
B43: 001.06.01.01 | C43: 4 | D43: ASSENTAMENTO DE PORCELANATO 120X120CM COM AC-III E NIVELADORES - PISO | E43: M2 | F43: 39.4259 | G43: 121.81332 | H43: 4802.5998 | I43: =SUMIF(Lançamentos!$F$7:$F$200,B43&"*",Lançamentos!$O$7:$O$200) -> 0 | J43: =H43-I43 -> 4802.5998 | K43: =IF(H43=0,0,I43/H43) -> 0
B44: 001.06.01.02 | C44: 4 | D44: FORNECIMENTO PORCELANATO PORTOBELLO 90X90CM AETERNA BIANCO | E44: M2 | F44: 39.4259 | G44: 241.5 | H44: 9521.3548 | I44: =SUMIF(Lançamentos!$F$7:$F$200,B44&"*",Lançamentos!$O$7:$O$200) -> 2660.36 | J44: =H44-I44 -> 6860.9949 | K44: =IF(H44=0,0,I44/H44) -> 0.27940982
B45: 001.06.01.03 | C45: 4 | D45: EXECUÇÃO DE REJUNTAMENTO EM PORCELANATO 120X120CM | E45: M2 | F45: 39.4259 | G45: 5.756755 | H45: 226.96525 | I45: =SUMIF(Lançamentos!$F$7:$F$200,B45&"*",Lançamentos!$O$7:$O$200) -> 0 | J45: =H45-I45 -> 226.96525 | K45: =IF(H45=0,0,I45/H45) -> 0
B46: 001.06.02 | C46: 3 | D46: REVESTIMENTO DE PAREDE | H46: =SUMIFS($H$8:$H$98,$B$8:$B$98,B46&"*",$C$8:$C$98,4) -> 9791.8164 | I46: =SUMIF(Lançamentos!$F$7:$F$200,B46&"*",Lançamentos!$O$7:$O$200) -> 0 | J46: =H46-I46 -> 9791.8164 | K46: =IF(H46=0,0,I46/H46) -> 0
B47: 001.06.02.01 | C47: 4 | D47: APLICAÇÃO DE PAPEL DE PAREDE, INCLUSO PREPARO DE SUPERFÍCIE E COLA - PAREDE | E47: M2 | F47: 24.342766 | G47: 166.15835 | H47: 4044.7538 | I47: =SUMIF(Lançamentos!$F$7:$F$200,B47&"*",Lançamentos!$O$7:$O$200) -> 0 | J47: =H47-I47 -> 4044.7538 | K47: =IF(H47=0,0,I47/H47) -> 0
B48: 001.06.02.02 | C48: 4 | D48: ASSENTAMENTO DE PORCELANATO 120X120CM COM AC-III E NIVELADORES - PAREDE | E48: M2 | F48: 6.45 | G48: 121.81332 | H48: 785.69591 | I48: =SUMIF(Lançamentos!$F$7:$F$200,B48&"*",Lançamentos!$O$7:$O$200) -> 0 | J48: =H48-I48 -> 785.69591 | K48: =IF(H48=0,0,I48/H48) -> 0
B49: 001.06.02.03 | C49: 4 | D49: FORNECIMENTO PORCELANATO PORTOBELLO 90X90CM AETERNA BIANCO | E49: M2 | F49: 7.4175 | G49: 241.5 | H49: 1791.3263 | I49: =SUMIF(Lançamentos!$F$7:$F$200,B49&"*",Lançamentos!$O$7:$O$200) -> 0 | J49: =H49-I49 -> 1791.3263 | K49: =IF(H49=0,0,I49/H49) -> 0
B50: 001.06.02.04 | C50: 4 | D50: EXECUÇÃO DE REJUNTAMENTO EM PORCELANATO 120X120CM | E50: M2 | F50: 4.975 | G50: 5.756755 | H50: 28.639856 | I50: =SUMIF(Lançamentos!$F$7:$F$200,B50&"*",Lançamentos!$O$7:$O$200) -> 0 | J50: =H50-I50 -> 28.639856 | K50: =IF(H50=0,0,I50/H50) -> 0
B51: 001.06.02.05 | C51: 4 | D51: FORNECIMENTO E EXECUÇÃO DE RODAPÉ METÁLICO | E51: M | F51: 41.08 | G51: 65.333244 | H51: 2683.8897 | I51: =SUMIF(Lançamentos!$F$7:$F$200,B51&"*",Lançamentos!$O$7:$O$200) -> 0 | J51: =H51-I51 -> 2683.8897 | K51: =IF(H51=0,0,I51/H51) -> 0
B52: 001.06.02.06 | C52: 4 | D52: FORNECIMENTO E EXECUÇÃO DE RODAPÉ SANTA LUZIA COM COLA E REJUNTE | E52: M | F52: 9.98 | G52: 45.842768 | H52: 457.51083 | I52: =SUMIF(Lançamentos!$F$7:$F$200,B52&"*",Lançamentos!$O$7:$O$200) -> 0 | J52: =H52-I52 -> 457.51083 | K52: =IF(H52=0,0,I52/H52) -> 0
B53: 001.07 | C53: 2 | D53: PINTURA | H53: =SUMIFS($H$8:$H$98,$B$8:$B$98,B53&"*",$C$8:$C$98,4) -> 18185.804 | I53: =SUMIF(Lançamentos!$F$7:$F$200,B53&"*",Lançamentos!$O$7:$O$200) -> 0 | J53: =H53-I53 -> 18185.804 | K53: =IF(H53=0,0,I53/H53) -> 0
B54: 001.07.01 | C54: 3 | D54: PINTURA DE PAREDE | H54: =SUMIFS($H$8:$H$98,$B$8:$B$98,B54&"*",$C$8:$C$98,4) -> 13865.793 | I54: =SUMIF(Lançamentos!$F$7:$F$200,B54&"*",Lançamentos!$O$7:$O$200) -> 0 | J54: =H54-I54 -> 13865.793 | K54: =IF(H54=0,0,I54/H54) -> 0
B55: 001.07.01.01 | C55: 4 | D55: FORNECIMENTO E EXECUÇÃO DE TEXTURA EFEITO CIMENTO QUEIMADO | E55: M2 | F55: 66.552366 | G55: 128.519 | H55: 8553.2435 | I55: =SUMIF(Lançamentos!$F$7:$F$200,B55&"*",Lançamentos!$O$7:$O$200) -> 0 | J55: =H55-I55 -> 8553.2435 | K55: =IF(H55=0,0,I55/H55) -> 0
B56: 001.07.01.02 | C56: 4 | D56: FORNECIMENTO E EXECUÇÃO DE PINTURA LATEX PVA COM DUAS DEMÃOS EM PAREDES EMASSADAS - INTERNAS | E56: M2 | F56: 71.46015 | G56: 64.975 | H56: 4643.1232 | I56: =SUMIF(Lançamentos!$F$7:$F$200,B56&"*",Lançamentos!$O$7:$O$200) -> 0 | J56: =H56-I56 -> 4643.1232 | K56: =IF(H56=0,0,I56/H56) -> 0
B57: 001.07.01.03 | C57: 4 | D57: FORNECIMENTO E EXECUÇÃO DE EMASSAMENTO - INTERNAS | E57: M2 | F57: 24.342766 | G57: 27.5 | H57: 669.42606 | I57: =SUMIF(Lançamentos!$F$7:$F$200,B57&"*",Lançamentos!$O$7:$O$200) -> 0 | J57: =H57-I57 -> 669.42606 | K57: =IF(H57=0,0,I57/H57) -> 0
B58: 001.07.02 | C58: 3 | D58: PINTURA DE TETO | H58: =SUMIFS($H$8:$H$98,$B$8:$B$98,B58&"*",$C$8:$C$98,4) -> 4320.0107 | I58: =SUMIF(Lançamentos!$F$7:$F$200,B58&"*",Lançamentos!$O$7:$O$200) -> 0 | J58: =H58-I58 -> 4320.0107 | K58: =IF(H58=0,0,I58/H58) -> 0
B59: 001.07.02.01 | C59: 4 | D59: FORNECIMENTO E EXECUÇÃO DE TEXTURA EFEITO CIMENTO QUEIMADO | E59: M2 | F59: 26.9855 | G59: 128.519 | H59: 3468.1495 | I59: =SUMIF(Lançamentos!$F$7:$F$200,B59&"*",Lançamentos!$O$7:$O$200) -> 0 | J59: =H59-I59 -> 3468.1495 | K59: =IF(H59=0,0,I59/H59) -> 0
B60: 001.07.02.02 | C60: 4 | D60: FORNECIMENTO E EXECUÇÃO DE PINTURA LATEX PVA COM DUAS DEMÃOS EM TETOS | E60: M2 | F60: 13.1106 | G60: 64.975 | H60: 851.86123 | I60: =SUMIF(Lançamentos!$F$7:$F$200,B60&"*",Lançamentos!$O$7:$O$200) -> 0 | J60: =H60-I60 -> 851.86123 | K60: =IF(H60=0,0,I60/H60) -> 0
B61: 001.08 | C61: 2 | D61: PEDRAS, LOUÇAS E METAIS | H61: =SUMIFS($H$8:$H$98,$B$8:$B$98,B61&"*",$C$8:$C$98,4) -> 12515.077 | I61: =SUMIF(Lançamentos!$F$7:$F$200,B61&"*",Lançamentos!$O$7:$O$200) -> 0 | J61: =H61-I61 -> 12515.077 | K61: =IF(H61=0,0,I61/H61) -> 0
B62: 001.08.01 | C62: 3 | D62: PEDRAS | H62: =SUMIFS($H$8:$H$98,$B$8:$B$98,B62&"*",$C$8:$C$98,4) -> 10136.31 | I62: =SUMIF(Lançamentos!$F$7:$F$200,B62&"*",Lançamentos!$O$7:$O$200) -> 0 | J62: =H62-I62 -> 10136.31 | K62: =IF(H62=0,0,I62/H62) -> 0
B63: 001.08.01.01 | C63: 4 | D63: FORNECIMENTO E ASSENTAMENTO DE BANCADA E TAMPO EM BRANCO ITAÚNAS | E63: M2 | F63: 2.749 | G63: 1559.88 | H63: 4288.11 | I63: =SUMIF(Lançamentos!$F$7:$F$200,B63&"*",Lançamentos!$O$7:$O$200) -> 0 | J63: =H63-I63 -> 4288.11 | K63: =IF(H63=0,0,I63/H63) -> 0
B64: 001.08.01.02 | C64: 4 | D64: FORNECIMENTO E ASSENTAMENTO DE TAMPO EM TRAVERTINO ROMANO BRUTO | E64: M2 | F64: 2.1 | G64: 2784.8571 | H64: 5848.2 | I64: =SUMIF(Lançamentos!$F$7:$F$200,B64&"*",Lançamentos!$O$7:$O$200) -> 0 | J64: =H64-I64 -> 5848.2 | K64: =IF(H64=0,0,I64/H64) -> 0
B65: 001.08.02 | C65: 3 | D65: LOUÇAS | H65: =SUMIFS($H$8:$H$98,$B$8:$B$98,B65&"*",$C$8:$C$98,4) -> 930.6922 | I65: =SUMIF(Lançamentos!$F$7:$F$200,B65&"*",Lançamentos!$O$7:$O$200) -> 0 | J65: =H65-I65 -> 930.6922 | K65: =IF(H65=0,0,I65/H65) -> 0
B66: 001.08.02.01 | C66: 4 | D66: FORNECIMENTO DE CUBA DE SOBREPOR RETANGULAR DECA L840 | E66: UND | F66: 1 | G66: 854.9 | H66: 854.9 | I66: =SUMIF(Lançamentos!$F$7:$F$200,B66&"*",Lançamentos!$O$7:$O$200) -> 0 | J66: =H66-I66 -> 854.9 | K66: =IF(H66=0,0,I66/H66) -> 0
B67: 001.08.02.02 | C67: 4 | D67: INSTALAÇÃO DE ACESSÓRIOS PARA CUBA DE APOIO | E67: UND | F67: 1 | G67: 75.7922 | H67: 75.7922 | I67: =SUMIF(Lançamentos!$F$7:$F$200,B67&"*",Lançamentos!$O$7:$O$200) -> 0 | J67: =H67-I67 -> 75.7922 | K67: =IF(H67=0,0,I67/H67) -> 0
B68: 001.08.03 | C68: 3 | D68: METAIS | H68: =SUMIFS($H$8:$H$98,$B$8:$B$98,B68&"*",$C$8:$C$98,4) -> 1448.0751 | I68: =SUMIF(Lançamentos!$F$7:$F$200,B68&"*",Lançamentos!$O$7:$O$200) -> 0 | J68: =H68-I68 -> 1448.0751 | K68: =IF(H68=0,0,I68/H68) -> 0
B69: 001.08.03.01 | C69: 4 | D69: FORNECIMENTO DE TORNEIRA DECA 1198.C33 POLO | E69: UND | F69: 1 | G69: 471.9 | H69: 471.9 | I69: =SUMIF(Lançamentos!$F$7:$F$200,B69&"*",Lançamentos!$O$7:$O$200) -> 0 | J69: =H69-I69 -> 471.9 | K69: =IF(H69=0,0,I69/H69) -> 0
B70: 001.08.03.02 | C70: 4 | D70: FORNECIMENTO DE CUBA DE AÇO INOX DUPLA 70X34CM REF. 94061/407 - TRAMONTINA | E70: UND | F70: 1 | G70: 449 | H70: 449 | I70: =SUMIF(Lançamentos!$F$7:$F$200,B70&"*",Lançamentos!$O$7:$O$200) -> 0 | J70: =H70-I70 -> 449 | K70: =IF(H70=0,0,I70/H70) -> 0
B71: 001.08.03.03 | C71: 4 | D71: FORNECIMENTO DE TORNEIRA DE MESA PARA COZINHA - 1167.C35 | E71: UND | F71: 1 | G71: 128.54 | H71: 128.54 | I71: =SUMIF(Lançamentos!$F$7:$F$200,B71&"*",Lançamentos!$O$7:$O$200) -> 0 | J71: =H71-I71 -> 128.54 | K71: =IF(H71=0,0,I71/H71) -> 0
B72: 001.08.03.04 | C72: 4 | D72: DUCHA HIGIÊNICA | E72: UND | F72: 1 | G72: 225 | H72: 225 | I72: =SUMIF(Lançamentos!$F$7:$F$200,B72&"*",Lançamentos!$O$7:$O$200) -> 0 | J72: =H72-I72 -> 225 | K72: =IF(H72=0,0,I72/H72) -> 0
B73: 001.08.03.05 | C73: 4 | D73: INSTALAÇÃO DE ACESSÓRIOS PARA CUBA DE AÇO INOX | E73: UND | F73: 1 | G73: 79.1822 | H73: 79.1822 | I73: =SUMIF(Lançamentos!$F$7:$F$200,B73&"*",Lançamentos!$O$7:$O$200) -> 0 | J73: =H73-I73 -> 79.1822 | K73: =IF(H73=0,0,I73/H73) -> 0
B74: 001.08.03.06 | C74: 4 | D74: INSTALAÇÃO DE ACESSÓRIOS PARA TORNEIRAS | E74: UND | F74: 2 | G74: 47.226439 | H74: 94.452878 | I74: =SUMIF(Lançamentos!$F$7:$F$200,B74&"*",Lançamentos!$O$7:$O$200) -> 0 | J74: =H74-I74 -> 94.452878 | K74: =IF(H74=0,0,I74/H74) -> 0
B75: 001.09 | C75: 2 | D75: INSTALAÇÕES | H75: =SUMIFS($H$8:$H$98,$B$8:$B$98,B75&"*",$C$8:$C$98,4) -> 32986.26 | I75: =SUMIF(Lançamentos!$F$7:$F$200,B75&"*",Lançamentos!$O$7:$O$200) -> 4411.16 | J75: =H75-I75 -> 28575.1 | K75: =IF(H75=0,0,I75/H75) -> 0.13372719
B76: 001.09.01 | C76: 3 | D76: INSTALAÇÕES ELÉTRICAS | H76: =SUMIFS($H$8:$H$98,$B$8:$B$98,B76&"*",$C$8:$C$98,4) -> 16400 | I76: =SUMIF(Lançamentos!$F$7:$F$200,B76&"*",Lançamentos!$O$7:$O$200) -> 0 | J76: =H76-I76 -> 16400 | K76: =IF(H76=0,0,I76/H76) -> 0
B77: 001.09.01.01 | C77: 4 | D77: FORNECIMENTO E EXECUÇÃO DE INSTALAÇÃO ELÉTRICAS E LUMINOTÉCNICAS | E77: OE | F77: 1 | G77: 16400 | H77: 16400 | I77: =SUMIF(Lançamentos!$F$7:$F$200,B77&"*",Lançamentos!$O$7:$O$200) -> 0 | J77: =H77-I77 -> 16400 | K77: =IF(H77=0,0,I77/H77) -> 0
B78: 001.09.02 | C78: 3 | D78: INSTALAÇÕES DE REDE E TELEFONE | H78: =SUMIFS($H$8:$H$98,$B$8:$B$98,B78&"*",$C$8:$C$98,4) -> 2653.38 | I78: =SUMIF(Lançamentos!$F$7:$F$200,B78&"*",Lançamentos!$O$7:$O$200) -> 0 | J78: =H78-I78 -> 2653.38 | K78: =IF(H78=0,0,I78/H78) -> 0
B79: 001.09.02.01 | C79: 4 | D79: FORNECIMENTO E EXECUÇÃO DE INSTALAÇÃO REDE/TELEFONE | E79: OE | F79: 1 | G79: 2653.38 | H79: 2653.38 | I79: =SUMIF(Lançamentos!$F$7:$F$200,B79&"*",Lançamentos!$O$7:$O$200) -> 0 | J79: =H79-I79 -> 2653.38 | K79: =IF(H79=0,0,I79/H79) -> 0
B80: 001.09.03 | C80: 3 | D80: INSTALAÇÕES HIDROSSANITÁRIAS | H80: =SUMIFS($H$8:$H$98,$B$8:$B$98,B80&"*",$C$8:$C$98,4) -> 861.72 | I80: =SUMIF(Lançamentos!$F$7:$F$200,B80&"*",Lançamentos!$O$7:$O$200) -> 0 | J80: =H80-I80 -> 861.72 | K80: =IF(H80=0,0,I80/H80) -> 0
B81: 001.09.03.01 | C81: 4 | D81: FORNECIMENTO E EXECUÇÃO DE INSTALAÇÃO HIDROSSANITÁRIA | E81: OE | F81: 1 | G81: 861.72 | H81: 861.72 | I81: =SUMIF(Lançamentos!$F$7:$F$200,B81&"*",Lançamentos!$O$7:$O$200) -> 0 | J81: =H81-I81 -> 861.72 | K81: =IF(H81=0,0,I81/H81) -> 0
B82: 001.09.04 | C82: 3 | D82: INSTALAÇÕES FRIGORIGENAS | H82: =SUMIFS($H$8:$H$98,$B$8:$B$98,B82&"*",$C$8:$C$98,4) -> 8200 | I82: =SUMIF(Lançamentos!$F$7:$F$200,B82&"*",Lançamentos!$O$7:$O$200) -> 4411.16 | J82: =H82-I82 -> 3788.84 | K82: =IF(H82=0,0,I82/H82) -> 0.53794634
B83: 001.09.04.01 | C83: 4 | D83: FORNECIMENTO E EXECUÇÃO DE INSTALAÇÃO FRIGORÍGENA | E83: OE | F83: 1 | G83: 8200 | H83: 8200 | I83: =SUMIF(Lançamentos!$F$7:$F$200,B83&"*",Lançamentos!$O$7:$O$200) -> 4411.16 | J83: =H83-I83 -> 3788.84 | K83: =IF(H83=0,0,I83/H83) -> 0.53794634
B84: 001.09.05 | C84: 3 | D84: INSTALAÇÕES DE COMBATE A INCÊNDIO | H84: =SUMIFS($H$8:$H$98,$B$8:$B$98,B84&"*",$C$8:$C$98,4) -> 4871.16 | I84: =SUMIF(Lançamentos!$F$7:$F$200,B84&"*",Lançamentos!$O$7:$O$200) -> 0 | J84: =H84-I84 -> 4871.16 | K84: =IF(H84=0,0,I84/H84) -> 0
B85: 001.09.05.01 | C85: 4 | D85: FORNECIMENTO E EXECUÇÃO DE INSTALAÇÃO DE COMBATE A INCÊNDIO | E85: OE | F85: 1 | G85: 4871.16 | H85: 4871.16 | I85: =SUMIF(Lançamentos!$F$7:$F$200,B85&"*",Lançamentos!$O$7:$O$200) -> 0 | J85: =H85-I85 -> 4871.16 | K85: =IF(H85=0,0,I85/H85) -> 0
B86: 001.10 | C86: 2 | D86: LIMPEZA | H86: =SUMIFS($H$8:$H$98,$B$8:$B$98,B86&"*",$C$8:$C$98,4) -> 1498.34 | I86: =SUMIF(Lançamentos!$F$7:$F$200,B86&"*",Lançamentos!$O$7:$O$200) -> 0 | J86: =H86-I86 -> 1498.34 | K86: =IF(H86=0,0,I86/H86) -> 0
B87: 001.10.01 | C87: 3 | D87: LIMPEZA | H87: =SUMIFS($H$8:$H$98,$B$8:$B$98,B87&"*",$C$8:$C$98,4) -> 1498.34 | I87: =SUMIF(Lançamentos!$F$7:$F$200,B87&"*",Lançamentos!$O$7:$O$200) -> 0 | J87: =H87-I87 -> 1498.34 | K87: =IF(H87=0,0,I87/H87) -> 0
B88: 001.10.01.01 | C88: 4 | D88: EXECUÇÃO DE LIMPEZA FINAL DE OBRA | E88: M2 | F88: 39.43 | G88: 38 | H88: 1498.34 | I88: =SUMIF(Lançamentos!$F$7:$F$200,B88&"*",Lançamentos!$O$7:$O$200) -> 0 | J88: =H88-I88 -> 1498.34 | K88: =IF(H88=0,0,I88/H88) -> 0
B89: 002 | C89: 1 | D89: AMBIENTAÇÃO | H89: =SUMIFS($H$8:$H$98,$B$8:$B$98,B89&"*",$C$8:$C$98,4) -> 128014.56 | I89: =SUMIF(Lançamentos!$F$7:$F$200,B89&"*",Lançamentos!$O$7:$O$200) -> 0 | J89: =H89-I89 -> 128014.56 | K89: =IF(H89=0,0,I89/H89) -> 0
B90: 002.01 | C90: 2 | D90: AMBIENTAÇÃO | H90: =SUMIFS($H$8:$H$98,$B$8:$B$98,B90&"*",$C$8:$C$98,4) -> 128014.56 | I90: =SUMIF(Lançamentos!$F$7:$F$200,B90&"*",Lançamentos!$O$7:$O$200) -> 0 | J90: =H90-I90 -> 128014.56 | K90: =IF(H90=0,0,I90/H90) -> 0
B91: 002.01.01 | C91: 3 | D91: MÓVEIS SOLTOS | H91: =SUMIFS($H$8:$H$98,$B$8:$B$98,B91&"*",$C$8:$C$98,4) -> 34800 | I91: =SUMIF(Lançamentos!$F$7:$F$200,B91&"*",Lançamentos!$O$7:$O$200) -> 0 | J91: =H91-I91 -> 34800 | K91: =IF(H91=0,0,I91/H91) -> 0
B92: 002.01.01.01 | C92: 4 | D92: FORNECIMENTO DE MÓVEIS SOLTOS | E92: VB | F92: 1 | G92: 34800 | H92: 34800 | I92: =SUMIF(Lançamentos!$F$7:$F$200,B92&"*",Lançamentos!$O$7:$O$200) -> 0 | J92: =H92-I92 -> 34800 | K92: =IF(H92=0,0,I92/H92) -> 0
B93: 002.01.02 | C93: 3 | D93: ILUMINAÇÃO | H93: =SUMIFS($H$8:$H$98,$B$8:$B$98,B93&"*",$C$8:$C$98,4) -> 19564.36 | I93: =SUMIF(Lançamentos!$F$7:$F$200,B93&"*",Lançamentos!$O$7:$O$200) -> 0 | J93: =H93-I93 -> 19564.36 | K93: =IF(H93=0,0,I93/H93) -> 0
B94: 002.01.02.01 | C94: 4 | D94: FORNECIMENTO DE ILUMINAÇÃO | E94: VB | F94: 1 | G94: 19564.36 | H94: 19564.36 | I94: =SUMIF(Lançamentos!$F$7:$F$200,B94&"*",Lançamentos!$O$7:$O$200) -> 0 | J94: =H94-I94 -> 19564.36 | K94: =IF(H94=0,0,I94/H94) -> 0
B95: 002.01.03 | C95: 3 | D95: MARCENARIA | H95: =SUMIFS($H$8:$H$98,$B$8:$B$98,B95&"*",$C$8:$C$98,4) -> 48810.2 | I95: =SUMIF(Lançamentos!$F$7:$F$200,B95&"*",Lançamentos!$O$7:$O$200) -> 0 | J95: =H95-I95 -> 48810.2 | K95: =IF(H95=0,0,I95/H95) -> 0
B96: 002.01.03.01 | C96: 4 | D96: FORNECIMENTO DE MARCENARIA | E96: VB | F96: 1 | G96: 48810.2 | H96: 48810.2 | I96: =SUMIF(Lançamentos!$F$7:$F$200,B96&"*",Lançamentos!$O$7:$O$200) -> 0 | J96: =H96-I96 -> 48810.2 | K96: =IF(H96=0,0,I96/H96) -> 0
B97: 002.01.04 | C97: 3 | D97: ELETRODOMÉSTICOS | H97: =SUMIFS($H$8:$H$98,$B$8:$B$98,B97&"*",$C$8:$C$98,4) -> 24840 | I97: =SUMIF(Lançamentos!$F$7:$F$200,B97&"*",Lançamentos!$O$7:$O$200) -> 0 | J97: =H97-I97 -> 24840 | K97: =IF(H97=0,0,I97/H97) -> 0
B98: 002.01.04.01 | C98: 4 | D98: FORNECIMENTO DE ELETRODOMÉSTICOS | E98: VB | F98: 1 | G98: 24840 | H98: 24840 | I98: =SUMIF(Lançamentos!$F$7:$F$200,B98&"*",Lançamentos!$O$7:$O$200) -> 0 | J98: =H98-I98 -> 24840 | K98: =IF(H98=0,0,I98/H98) -> 0

Sheet Lançamentos
B2: Controle Financeiro · Lançamentos
B3: Cada lançamento é vinculado a um código da EAP do orçamento (coluna F) para o comparativo Orçado x Realizado
B4: Legenda: fundo amarelo claro = preenchimento manual do vínculo com o orçamento. Coluna G é automática (item da EAP).
B6: Nº | C6: Data e hora | D6: Projeto | E6: Centro de custo | F6: Código EAP | G6: Item do orçamento (EAP) | H6: Descrição | I6: Favorecido | J6: Instituição (destino) | K6: Tipo | L6: Pagador (origem) | M6: Instituição (origem) | N6: ID da transação | O6: Valor (R$) | P6: Anexo | Q6: Observação
B7: 1 | C7: 46288.443 | D7: Clínica Sensi | E7: Instalações Frigorígenas | F7: 001.09.04.01 | G7: =IFERROR(INDEX('Orçado x Realizado'!$D$8:$D$200,MATCH(F7,'Orçado x Realizado'!$B$8:$B$200,0)),"código não encontrado") -> FORNECIMENTO E EXECUÇÃO DE INSTALAÇÃO FRIGORÍGENA | H7: Aquisição de tubos e conexões em cobre, esponjosos e itens elétricos | I7: Alexandre Araujo da Silva | J7: Caixa Econômica Federal | K7: Pix | L7: Vitoria Brenda Borges Aquino | M7: Nubank (NU Pagamentos - IP) | N7: E18236120202609231338s104aa8169c | O7: 4411.16 | P7: Ver anexo | Q7: Vínculo assumido: item 001.09.04.01 (Instalação frigorígena). Parte da compra são itens elétricos — confirmar se deve ser rateada com 001.09.01.01.
B8: 2 | C8: 46286.702 | D8: Clínica Sensi | E8: Revestimento Cerâmico | F8: 001.06.01.02 | G8: =IFERROR(INDEX('Orçado x Realizado'!$D$8:$D$200,MATCH(F8,'Orçado x Realizado'!$B$8:$B$200,0)),"código não encontrado") -> FORNECIMENTO PORCELANATO PORTOBELLO 90X90CM AETERNA BIANCO | H8: Pagamento à Cerâmica Cerbras (revestimento cerâmico) | I8: Cerâmica Cerbras | J8: Banco Santander (Brasil) S.A. | K8: Pix | L8: Sabrina Amabili Educação LTDA | M8: Nubank (NU Pagamentos - IP) | N8: E18236120202609211951s12412875f4 | O8: 2660.36 | P8: Ver anexo | Q8: Vínculo assumido: fornecimento de porcelanato de PISO (001.06.01.02); se for parede, usar 001.06.02.03.
B201: TOTAL | O201: =SUM(O7:O200) -> 7071.52

Sheet Anexos
B2: Anexos · Comprovantes
B3: Numeração igual à coluna Nº da aba Lançamentos
B5: 01 · Alexandre Araujo da Silva · R$ 4.411,16 | C5: 02 · Cerâmica Cerbras · R$ 2.660,36
B6: Instalações Frigorígenas · 23/09/2026 | C6: Revestimento Cerâmico · 21/09/2026
